honeybee_designbuilder/__init__.py
honeybee_designbuilder/__main__.py
honeybee_designbuilder/_extend_honeybee.py
honeybee_designbuilder/writer.py
honeybee_designbuilder/_templates/Assembly.xml
honeybee_designbuilder/_templates/Default.xml
honeybee_designbuilder/_templates/Full.xml
honeybee_designbuilder/cli/__init__.py
honeybee_designbuilder/cli/translate.py
honeybee_designbuilder/properties/__init__.py
honeybee_designbuilder/properties/model.py
honeybee_designbuilder/properties/room.py
honeybee_designbuilder-0.4.0.dist-info/licenses/LICENSE
honeybee_designbuilder-0.4.0.dist-info/METADATA
honeybee_designbuilder-0.4.0.dist-info/WHEEL
honeybee_designbuilder-0.4.0.dist-info/entry_points.txt
honeybee_designbuilder-0.4.0.dist-info/top_level.txt
honeybee_designbuilder-0.4.0.dist-info/RECORD
