Metadata-Version: 2.4
Name: honeybee-designbuilder
Version: 0.4.0
Summary: Honeybee extension for translating HBJSON files to dsbXML files for DesignBuilder
Home-page: https://github.com/ladybug-tools/honeybee-designbuilder
Author: Ladybug Tools
Author-email: info@ladybug.tools
License: AGPL-3.0
Classifier: Programming Language :: Python :: 3.9
Classifier: Programming Language :: Python :: 3.10
Classifier: Programming Language :: Python :: 3.11
Classifier: Programming Language :: Python :: 3.12
Classifier: Programming Language :: Python :: Implementation :: CPython
Classifier: Operating System :: OS Independent
License-File: LICENSE
Requires-Dist: honeybee-energy>=1.116.102
Provides-Extra: standards
Requires-Dist: honeybee-energy-standards>=2.3.0; extra == "standards"
Dynamic: author
Dynamic: author-email
Dynamic: classifier
Dynamic: description
Dynamic: description-content-type
Dynamic: home-page
Dynamic: license
Dynamic: license-file
Dynamic: provides-extra
Dynamic: requires-dist
Dynamic: summary
